pyDgzq/UI.py
pyDgzq/__init__.py
pyDgzq/md5.py
pyDgzq/ocr.py
pyDgzq/runner.py
pyDgzq/tasks.py
pyDgzq/ui_elements.py
PyDgzq-0.0.12.dist-info/METADATA
PyDgzq-0.0.12.dist-info/WHEEL
PyDgzq-0.0.12.dist-info/top_level.txt
PyDgzq-0.0.12.dist-info/RECORD
